LICENSE
MANIFEST.in
README.md
requirements.txt
setup.py
alpha_homora_v2/__init__.py
alpha_homora_v2/_config.py
alpha_homora_v2/oracles.py
alpha_homora_v2/position.py
alpha_homora_v2/provider.py
alpha_homora_v2/receipt.py
alpha_homora_v2/spell.py
alpha_homora_v2/token.py
alpha_homora_v2/util.py
alpha_homora_v2.egg-info/PKG-INFO
alpha_homora_v2.egg-info/SOURCES.txt
alpha_homora_v2.egg-info/dependency_links.txt
alpha_homora_v2.egg-info/requires.txt
alpha_homora_v2.egg-info/top_level.txt
alpha_homora_v2/abi/AggregatorOracle_ABI.json
alpha_homora_v2/abi/BoostedMasterChefJoe_custom_ABI.json
alpha_homora_v2/abi/ERC20_ABI.json
alpha_homora_v2/abi/HomoraBankABI.json
alpha_homora_v2/abi/ISafeOracle_ABI.json
alpha_homora_v2/abi/MasterChefJoeV2_ABI.json
alpha_homora_v2/abi/MasterChefJoeV3_ABI.json
alpha_homora_v2/abi/Minichef_v2ABI.json
alpha_homora_v2/abi/PangolinLiquidityABI.json
alpha_homora_v2/abi/PangolinSpellV2.json
alpha_homora_v2/abi/SushiswapSpellV1.json
alpha_homora_v2/abi/TraderJoeLP_ABI.json
alpha_homora_v2/abi/TraderJoeSpellV1ABI.json
alpha_homora_v2/abi/USDC.e_ABI.json
alpha_homora_v2/abi/WBoostedMasterChefJoe_ABI.json
alpha_homora_v2/abi/WERC20ABI.json
alpha_homora_v2/abi/WMasterChefJoeV3_ABI.json
alpha_homora_v2/abi/WMasterchefJoeV2_ABI.json
alpha_homora_v2/abi/WMiniChefPNG.json
alpha_homora_v2/abi/pool.json
alpha_homora_v2/abi/tok.json
alpha_homora_v2/abi/tokenFactors.json
alpha_homora_v2/resources/__init__.py
alpha_homora_v2/resources/abi_reference.py
alpha_homora_v2/resources/token_metadata.csv
alpha_homora_v2/resources/__pycache__/__init__.cpython-39.pyc
alpha_homora_v2/resources/__pycache__/abi_reference.cpython-39.pyc