Metadata-Version: 2.1
Name: alpha-homora-v2
Version: 2.0.3
Summary: An unofficial Python package that wraps Alpha Homora V2 position smart contracts.
Home-page: https://github.com/PathX-Projects/Alpha-Homora-V2-Python
Author: Harrison Schick
Author-email: hschickdevs@gmail.com
License: Apache-2.0
Platform: UNKNOWN
Requires-Python: >=3.9
License-File: LICENSE
